pygameextra_calculator/__init__.py
pygameextra_calculator/build/scripts-3.8/pge-calculator
pygameextra_calculator/command/pge-calculator
pygameextra_calculator/dist/pge_calculator-0.0.0-py3.8.egg
pygameextra_calculator/pge_calculator.egg-info/PKG-INFO
pygameextra_calculator/pge_calculator.egg-info/SOURCES.txt
pygameextra_calculator/pge_calculator.egg-info/dependency_links.txt
pygameextra_calculator/pge_calculator.egg-info/top_level.txt
pygameextra_calculator/setup.py
pygameextra_calculator-1.6.dist-info/WHEEL
pygameextra_calculator-1.6.dist-info/METADATA
pygameextra_calculator-1.6.dist-info/RECORD
