Metadata-Version: 2.1
Name: pygameextra-calculator
Version: 1.6
Summary: a simple pygame extra calculator that can be ran with shell
License: BSD-3-Clause
Author: RedstoneHair
Requires-Python: >=3.5,<4.0
Classifier: License :: OSI Approved :: BSD License
Classifier: Programming Language :: Python :: 3
Classifier: Programming Language :: Python :: 3.5
Classifier: Programming Language :: Python :: 3.6
Classifier: Programming Language :: Python :: 3.7
Classifier: Programming Language :: Python :: 3.8
Classifier: Programming Language :: Python :: 3.9
Requires-Dist: pygame (>=1.9.6,<2.0.0)
Requires-Dist: pygameextra
